setup.py
distributions/Binomialdistribution.py
distributions/Gaussiandistribution.py
distributions/Generaldistribution.py
distributions/__init__.py
pypi_distributions.egg-info/PKG-INFO
pypi_distributions.egg-info/SOURCES.txt
pypi_distributions.egg-info/dependency_links.txt
pypi_distributions.egg-info/not-zip-safe
pypi_distributions.egg-info/top_level.txt